fluidly_pubsub-0.3.0-py3.9-nspkg.pth
fluidly/pubsub/__init__.py
fluidly/pubsub/base_subscriber.py
fluidly/pubsub/exceptions.py
fluidly/pubsub/fake_publisher.py
fluidly/pubsub/message.py
fluidly/pubsub/publisher.py
fluidly/pubsub/py.typed
fluidly/pubsub/subscriber.py
fluidly/pubsub/tests.py
fluidly_pubsub-0.3.0.dist-info/METADATA
fluidly_pubsub-0.3.0.dist-info/WHEEL
fluidly_pubsub-0.3.0.dist-info/namespace_packages.txt
fluidly_pubsub-0.3.0.dist-info/top_level.txt
fluidly_pubsub-0.3.0.dist-info/RECORD
